pydapper/__init__.py
pydapper/bigquery/__init__.py
pydapper/bigquery/google_bigquery_client.py
pydapper/commands.py
pydapper/dsn_parser.py
pydapper/exceptions.py
pydapper/main.py
pydapper/mssql/__init__.py
pydapper/mssql/pymssql.py
pydapper/mysql/__init__.py
pydapper/mysql/mysql_connector_python.py
pydapper/oracle/__init__.py
pydapper/oracle/oracledb.py
pydapper/postgresql/__init__.py
pydapper/postgresql/aiopg.py
pydapper/postgresql/psycopg2.py
pydapper/postgresql/psycopg3.py
pydapper/py.typed
pydapper/sqlite/__init__.py
pydapper/sqlite/sqlite3.py
pydapper/types.py
pydapper/utils.py
pydapper-0.11.1.dist-info/LICENSE
pydapper-0.11.1.dist-info/METADATA
pydapper-0.11.1.dist-info/WHEEL
pydapper-0.11.1.dist-info/RECORD
