Metadata-Version: 2.1
Name: pydapper
Version: 0.11.1
Summary: A pure python lib inspired by the dotnet lib dapper
License: MIT
Author: Zach Schumacher
Author-email: zschu15@gmail.com
Requires-Python: >=3.9,<3.14
Classifier: Development Status :: 5 - Production/Stable
Classifier: Environment :: Console
Classifier: Environment :: MacOS X
Classifier: Intended Audience :: Developers
Classifier: Intended Audience :: Information Technology
Classifier: Intended Audience :: System Administrators
Classifier: License :: OSI Approved :: MIT License
Classifier: Operating System :: POSIX :: Linux
Classifier: Operating System :: Unix
Classifier: Programming Language :: Python
Classifier: Programming Language :: Python :: 3
Classifier: Programming Language :: Python :: 3.9
Classifier: Programming Language :: Python :: 3.10
Classifier: Programming Language :: Python :: 3.11
Classifier: Programming Language :: Python :: 3.12
Classifier: Programming Language :: Python :: 3 :: Only
Classifier: Programming Language :: Python :: 3.13
Classifier: Topic :: Database
Classifier: Topic :: Database :: Database Engines/Servers
Classifier: Topic :: Internet
Classifier: Topic :: Software Development :: Libraries :: Python Modules
Provides-Extra: aiopg
Provides-Extra: all
Provides-Extra: google-cloud-bigquery
Provides-Extra: google-cloud-bigquery-storage
Provides-Extra: mysql-connector-python
Provides-Extra: oracledb
Provides-Extra: psycopg
Provides-Extra: psycopg2
Provides-Extra: pymssql
Requires-Dist: aiopg (>=1.4.0,<2.0.0) ; extra == "aiopg" or extra == "all"
Requires-Dist: cached-property (>=2.0.1,<3.0.0)
Requires-Dist: coro-context-manager (==0.2.1)
Requires-Dist: dsnparse (>=0.2.1,<0.3.0)
Requires-Dist: google-cloud-bigquery (>=3.29.0,<4.0.0) ; extra == "google-cloud-bigquery" or extra == "all"
Requires-Dist: google-cloud-bigquery-storage (>=2.27.0,<3.0.0) ; extra == "google-cloud-bigquery-storage" or extra == "all"
Requires-Dist: mysql-connector-python (>=9.2.0,<10.0.0) ; extra == "mysql-connector-python" or extra == "all"
Requires-Dist: numpy ; extra == "google-cloud-bigquery-storage" or extra == "all"
Requires-Dist: oracledb (>=2.5.1,<3.0.0) ; extra == "oracledb" or extra == "all"
Requires-Dist: psycopg2-binary (>=2.9.10,<3.0.0) ; extra == "psycopg2"
Requires-Dist: psycopg[binary] (>=3.2.4,<4.0.0) ; extra == "psycopg" or extra == "all"
Requires-Dist: pyarrow ; extra == "google-cloud-bigquery-storage" or extra == "all"
Requires-Dist: pymssql (>=2.3.2,<3.0.0) ; extra == "pymssql" or extra == "all"
Requires-Dist: types-psycopg2 (>=2.9.4,<3.0.0) ; extra == "psycopg2" or extra == "all"
Requires-Dist: types-pymssql (>=2.1.0,<3.0.0) ; extra == "pymssql" or extra == "all"
